fake_git_history/__init__.py
fake_git_history/__main__.py
fake_git_history/cli.py
fake_git_history-1.0.3.dist-info/METADATA
fake_git_history-1.0.3.dist-info/WHEEL
fake_git_history-1.0.3.dist-info/entry_points.txt
fake_git_history-1.0.3.dist-info/licenses/LICENSE
fake_git_history-1.0.3.dist-info/RECORD
