Metadata-Version: 2.4
Name: fake-git-history
Version: 1.0.3
Summary: A simple utility to generate fake git history for a Github and Gitlab profile.
Project-URL: Homepage, https://github.com/Almas-Ali/fake-git-history
Project-URL: Documentation, https://github.com/Almas-Ali/fake-git-history#readme
Project-URL: Repository, https://github.com/Almas-Ali/fake-git-history
Project-URL: Bug Tracker, https://github.com/Almas-Ali/fake-git-history/issues
Author-email: "Md. Almas Ali" <almaspr3@gmail.com>
Maintainer-email: "Md. Almas Ali" <almaspr3@gmail.com>
License: MIT License
License-File: LICENSE
Keywords: cli,cli-interface,cli-tool,cli-utility,command-line,command-line-interface,command-line-tool,command-line-utility,commit,commit-history,commit-history-generator,commit-history-generator-cli,commit-history-generator-cli-tool,commit-history-generator-command-line,commit-history-generator-command-line-interface,commit-history-generator-command-line-tool,commit-history-generator-command-line-utility,commit-history-generator-interface,commit-history-generator-tool,commit-history-generator-u
Classifier: Development Status :: 5 - Production/Stable
Classifier: Environment :: Console
Classifier: Intended Audience :: Developers
Classifier: License :: OSI Approved :: MIT License
Classifier: Natural Language :: English
Classifier: Programming Language :: Python
Classifier: Programming Language :: Python :: 3
Classifier: Programming Language :: Python :: 3 :: Only
Classifier: Programming Language :: Python :: 3.7
Classifier: Programming Language :: Python :: 3.8
Classifier: Programming Language :: Python :: 3.9
Classifier: Programming Language :: Python :: 3.10
Classifier: Programming Language :: Python :: 3.11
Classifier: Programming Language :: Python :: 3.12
Classifier: Programming Language :: Python :: 3.13
Requires-Python: >=3.7
Requires-Dist: rong==0.0.3
